README
setup.py
muxminos/__init__.py
muxminos/cmd.py
muxminos/conf.py
muxminos.egg-info/PKG-INFO
muxminos.egg-info/SOURCES.txt
muxminos.egg-info/dependency_links.txt
muxminos.egg-info/entry_points.txt
muxminos.egg-info/requires.txt
muxminos.egg-info/top_level.txt