Metadata-Version: 1.0
Name: muxminos
Version: 0.3.9
Summary: A cmd tool for tmuxinator generating configuration file for minos
Home-page: UNKNOWN
Author: hujianxin
Author-email: hujianxin@xiaomi.com
License: Apache License
Platform: UNKNOWN
